danmu_abc/__init__.py
danmu_abc/client.py
danmu_abc/conn.py
danmu_abc-0.1.5.dist-info/LICENSE
danmu_abc-0.1.5.dist-info/METADATA
danmu_abc-0.1.5.dist-info/WHEEL
danmu_abc-0.1.5.dist-info/top_level.txt
danmu_abc-0.1.5.dist-info/RECORD
