Metadata-Version: 2.1
Name: danmu-abc
Version: 0.1.5
Summary: Danmu for humans.
Home-page: https://github.com/yjqiang/danmu
Author: yjqang
Author-email: yjqiang01@gmail.com
License: MIT
Keywords: danmu,huya,bilibili,douyu
Platform: UNKNOWN
Classifier: Intended Audience :: Developers
Classifier: License :: OSI Approved :: MIT License
Classifier: Programming Language :: Python
Classifier: Programming Language :: Python :: 3
Classifier: Programming Language :: Python :: 3.6
Classifier: Programming Language :: Python :: 3.7
Classifier: Programming Language :: Python :: 3.8
Requires-Python: >=3.6
Requires-Dist: aiohttp (<4.0.0,>=3.7.3)
